constrained_linkage/__init__.py
constrained_linkage/constrained_linkage.py
constrained_linkage-1.0.1.dist-info/METADATA
constrained_linkage-1.0.1.dist-info/WHEEL
constrained_linkage-1.0.1.dist-info/licenses/LICENSE
constrained_linkage-1.0.1.dist-info/RECORD
