Metadata-Version: 2.4
Name: constrained-linkage
Version: 1.0.1
Summary: Hierarchical agglomerative clustering with soft constraints (SciPy-compatible Z).
Project-URL: Homepage, https://github.com/jonnevd/constrained-linkage
Project-URL: Issues, https://github.com/jonnevd/constrained-linkage/issues
Project-URL: Documentation, https://github.com/jonnevd/constrained-linkage#readme
Project-URL: Source, https://github.com/jonnevd/constrained-linkage
Author-email: Jonne van Dreven <jva@bth.se>
License: MIT
License-File: LICENSE
Keywords: HAC,clustering,constraints,hierarchical,linkage
Classifier: Intended Audience :: Science/Research
Classifier: License :: OSI Approved :: MIT License
Classifier: Operating System :: OS Independent
Classifier: Programming Language :: Python :: 3
Classifier: Topic :: Scientific/Engineering :: Artificial Intelligence
Classifier: Topic :: Scientific/Engineering :: Information Analysis
Requires-Python: >=3.8
Requires-Dist: numpy>=1.20
Provides-Extra: test
Requires-Dist: pytest-cov>=4; extra == 'test'
Requires-Dist: pytest>=7; extra == 'test'
Requires-Dist: scipy>=1.8; extra == 'test'
